README.rst
setup.cfg
setup.py
venom/__init__.py
venom/converter.py
venom/exceptions.py
venom/fields.py
venom/message.py
venom/util.py
venom.egg-info/PKG-INFO
venom.egg-info/SOURCES.txt
venom.egg-info/dependency_links.txt
venom.egg-info/not-zip-safe
venom.egg-info/requires.txt
venom.egg-info/top_level.txt
venom/common/__init__.py
venom/common/converters.py
venom/common/fields.py
venom/common/messages.py
venom/common/types.py
venom/protocol/__init__.py
venom/protocol/protocol.py
venom/protocol/transcode.py
venom/rpc/__init__.py
venom/rpc/context.py
venom/rpc/inspection.py
venom/rpc/method.py
venom/rpc/proxy.py
venom/rpc/resolver.py
venom/rpc/service.py
venom/rpc/stub.py
venom/rpc/comms/__init__.py
venom/rpc/comms/aiohttp.py
venom/rpc/comms/grpc.py
venom/rpc/reflect/__init__.py
venom/rpc/reflect/openapi.py
venom/rpc/reflect/reflect.py
venom/rpc/reflect/service.py
venom/rpc/reflect/stubs.py
venom/rpc/test_utils/__init__.py
venom/validation/__init__.py
venom/validation/_validators.py
venom/validation/schema.py